flexynesis/__init__.py
flexynesis/__main__.py
flexynesis/config.py
flexynesis/data.py
flexynesis/feature_selection.py
flexynesis/generate_coexpression_network.py
flexynesis/main.py
flexynesis/modules.py
flexynesis/utils.py
flexynesis/models/__init__.py
flexynesis/models/crossmodal_pred.py
flexynesis/models/direct_pred.py
flexynesis/models/gnn_early.py
flexynesis/models/supervised_vae.py
flexynesis/models/triplet_encoder.py
flexynesis-1.1.6.dist-info/licenses/LICENSE
flexynesis-1.1.6.dist-info/METADATA
flexynesis-1.1.6.dist-info/WHEEL
flexynesis-1.1.6.dist-info/entry_points.txt
flexynesis-1.1.6.dist-info/top_level.txt
flexynesis-1.1.6.dist-info/RECORD
