Metadata-Version: 2.4
Name: flexynesis
Version: 1.1.6
Summary: A deep-learning based multi-omics bulk sequencing data integration suite with a focus on (pre-)clinical endpoint prediction.
Author-email: Bora Uyar <bora.uyar@mdc-berlin.de>, Taras Savchyn <Taras.Savchyn@mdc-berlin.de>, Ricardo Wurmus <Ricardo.Wurmus@mdc-berlin.de>, Ahmet Sarigun <Ahmet.Sariguen@mdc-berlin.de>
License: # PolyForm Noncommercial License 1.0.0
Project-URL: homepage, https://github.com/BIMSBbioinfo/flexynesis
Classifier: Programming Language :: Python :: 3
Classifier: Programming Language :: Python :: 3.11
Classifier: Programming Language :: Python :: 3.12
Classifier: Programming Language :: Python :: 3 :: Only
Requires-Python: >=3.11
License-File: LICENSE
Requires-Dist: matplotlib
Requires-Dist: numpy
Requires-Dist: pandas
Requires-Dist: lightning
Requires-Dist: pyyaml
Requires-Dist: scikit-optimize
Requires-Dist: scipy
Requires-Dist: seaborn
Requires-Dist: torch
Requires-Dist: torchvision
Requires-Dist: tqdm
Requires-Dist: umap-learn
Requires-Dist: rich
Requires-Dist: captum
Requires-Dist: ipywidgets
Requires-Dist: torch_geometric
Requires-Dist: ipykernel
Requires-Dist: lifelines
Requires-Dist: papermill
Requires-Dist: scikit-survival
Requires-Dist: python-louvain
Requires-Dist: xgboost
Requires-Dist: pot
Requires-Dist: geomloss
Requires-Dist: plotnine
Requires-Dist: safetensors
Provides-Extra: test
Requires-Dist: pytest; extra == "test"
Dynamic: license-file
